{
  "TripeaksToolsWebData": "/绝对路径/TripeaksToolsWebData (发版流程存档目录,必须在 server 目录之外)",
  "TripeaksClient": "/abs/TripeaksClient (本地工作副本路径,发版流程用)",
  "TripeaksResources": "/abs/TripeaksResources",
  "TripeaksJourneyConfig": "/abs/TripeaksJourneyConfig",
  "TripeaksAdventureConfig": "/abs/TripeaksAdventureConfig",
  "TripeaksLevelConfig": "/abs/TripeaksLevelConfig",
  "feishu": {
    "mcp_token": "飞书项目 MCP token (m-xxxx)",
    "webhook": "测试群自定义机器人 webhook (https://open.feishu.cn/open-apis/bot/v2/hook/xxxx)",
    "webhookSecret": "(可选)机器人签名校验密钥,没开签名就删掉这行"
  },
  "jenkins": {
    "baseUrl": "http://10.10.31.17:8080",
    "otaJob": { "TP1": "Tripeaks1_OTA", "TP4": "4P_OTA" }
  },
  "shushu": {
    "token": "数数 querySql token"
  },
  "gsheet": {
    "type": "service_account",
    "project_id": "...",
    "private_key_id": "...",
    "private_key": "-----BEGIN PRIVATE KEY-----\\n...\\n-----END PRIVATE KEY-----\\n",
    "client_email": "xxx@xxx.iam.gserviceaccount.com",
    "client_id": "...",
    "token_uri": "https://oauth2.googleapis.com/token"
  }
}
